LICENSE
README.md
setup.py
ChainExAPI.egg-info/PKG-INFO
ChainExAPI.egg-info/SOURCES.txt
ChainExAPI.egg-info/dependency_links.txt
ChainExAPI.egg-info/requires.txt
ChainExAPI.egg-info/top_level.txt
chainex/__init__.py
chainex/chainex.py