Metadata-Version: 2.1
Name: ChainExAPI
Version: 0.1.0
Summary: Python client library for interacting with the ChainEx cryptocurrency exchange API.
Home-page: https://github.com/RichardAtCT//chainexapi
Author: Richard A
Author-email: richardatk01@gmail.com
License: UNKNOWN
Keywords: chainex cryptocurrency exchange api
Platform: UNKNOWN
Classifier: Development Status :: 3 - Alpha
Classifier: Intended Audience :: Developers
Classifier: Topic :: Software Development :: Libraries :: Python Modules
Classifier: License :: OSI Approved :: MIT License
Classifier: Programming Language :: Python :: 3
Classifier: Programming Language :: Python :: 3.6
Classifier: Programming Language :: Python :: 3.7
Classifier: Programming Language :: Python :: 3.8
Classifier: Programming Language :: Python :: 3.9
Requires-Python: >=3.6
License-File: LICENSE
